AUTHORS.rst
CONTRIBUTING.rst
HISTORY.rst
LICENSE
MANIFEST.in
README.rst
setup.py
mdx_twitter/__init__.py
mdx_twitter/extension.py
mdx_twitter/settings.py
mdx_twitter.egg-info/PKG-INFO
mdx_twitter.egg-info/SOURCES.txt
mdx_twitter.egg-info/dependency_links.txt
mdx_twitter.egg-info/not-zip-safe
mdx_twitter.egg-info/requires.txt
mdx_twitter.egg-info/top_level.txt