Metadata-Version: 1.1
Name: mdx-twitter
Version: 0.2.2
Summary: Markdown extension for embedding tweets
Home-page: https://github.com/zen4ever/mdx-twitter
Author: Andrii Kurinnyi
Author-email: andrew@marpasoft.com
License: BSD
Keywords: Markdown,Twitter
Platform: UNKNOWN
Classifier: Development Status :: 2 - Pre-Alpha
Classifier: Intended Audience :: Developers
Classifier: License :: OSI Approved :: BSD License
Classifier: Natural Language :: English
Classifier: Programming Language :: Python :: 2
Classifier: Programming Language :: Python :: 2.6
Classifier: Programming Language :: Python :: 2.7
